sas2nb/__init__.py
sas2nb/_version.py
sas2nb/convertSAS2nb.py
sas2nb/handlers.py
sas2nb/labextension/build_log.json
sas2nb/labextension/package.json
sas2nb/labextension/static/lib_index_js.0de9f797445bafb2c71d.js
sas2nb/labextension/static/lib_index_js.0de9f797445bafb2c71d.js.map
sas2nb/labextension/static/remoteEntry.94b65b55376d6eca8161.js
sas2nb/labextension/static/remoteEntry.94b65b55376d6eca8161.js.map
sas2nb/labextension/static/style.js
sas2nb/labextension/static/style_index_js.478ccf6e9f9069ce9df4.js
sas2nb/labextension/static/style_index_js.478ccf6e9f9069ce9df4.js.map
sas2nb/labextension/static/vendors-node_modules_css-loader_dist_runtime_api_js-node_modules_css-loader_dist_runtime_cssW-926fd9.256de27b3f3f9cbb10e2.js
sas2nb/labextension/static/vendors-node_modules_css-loader_dist_runtime_api_js-node_modules_css-loader_dist_runtime_cssW-926fd9.256de27b3f3f9cbb10e2.js.map
sas2nb-0.1.0.data/data/etc/jupyter/jupyter_server_config.d/sas2nb.json
sas2nb-0.1.0.data/data/share/jupyter/labextensions/sas2nb/build_log.json
sas2nb-0.1.0.data/data/share/jupyter/labextensions/sas2nb/install.json
sas2nb-0.1.0.data/data/share/jupyter/labextensions/sas2nb/package.json
sas2nb-0.1.0.data/data/share/jupyter/labextensions/sas2nb/static/lib_index_js.0de9f797445bafb2c71d.js
sas2nb-0.1.0.data/data/share/jupyter/labextensions/sas2nb/static/lib_index_js.0de9f797445bafb2c71d.js.map
sas2nb-0.1.0.data/data/share/jupyter/labextensions/sas2nb/static/remoteEntry.94b65b55376d6eca8161.js
sas2nb-0.1.0.data/data/share/jupyter/labextensions/sas2nb/static/remoteEntry.94b65b55376d6eca8161.js.map
sas2nb-0.1.0.data/data/share/jupyter/labextensions/sas2nb/static/style.js
sas2nb-0.1.0.data/data/share/jupyter/labextensions/sas2nb/static/style_index_js.478ccf6e9f9069ce9df4.js
sas2nb-0.1.0.data/data/share/jupyter/labextensions/sas2nb/static/style_index_js.478ccf6e9f9069ce9df4.js.map
sas2nb-0.1.0.dist-info/LICENSE
sas2nb-0.1.0.dist-info/METADATA
sas2nb-0.1.0.dist-info/WHEEL
sas2nb-0.1.0.dist-info/top_level.txt
sas2nb-0.1.0.dist-info/RECORD
