Metadata-Version: 2.1
Name: sas2nb
Version: 0.1.0
Summary: A Jupyter Lab extension to convert *.sas files to *.ipynb splitting on run boundaries.
Home-page: https://github.com/jld23/sas_kernel_ext
Author: Jared Dean
Author-email: jared.dean@gmail.com
License: BSD-3-Clause
Keywords: Jupyter,JupyterLab,JupyterLab3
Platform: Linux
Platform: Mac OS X
Platform: Windows
Classifier: License :: OSI Approved :: BSD License
Classifier: Programming Language :: Python
Classifier: Programming Language :: Python :: 3
Classifier: Programming Language :: Python :: 3.6
Classifier: Programming Language :: Python :: 3.7
Classifier: Programming Language :: Python :: 3.8
Classifier: Programming Language :: Python :: 3.9
Classifier: Framework :: Jupyter
Requires-Python: >=3.6
Requires-Dist: jupyterlab (~=3.0)
